deelink/__init__.py
deelink/dez.py
deelink-2.0.0.dist-info/LICENSE
deelink-2.0.0.dist-info/METADATA
deelink-2.0.0.dist-info/WHEEL
deelink-2.0.0.dist-info/entry_points.txt
deelink-2.0.0.dist-info/top_level.txt
deelink-2.0.0.dist-info/RECORD
